pyke_mcp/__init__.py
pyke_mcp/engine.py
pyke_mcp/server.py
pyke_mcp-0.1.1.dist-info/METADATA
pyke_mcp-0.1.1.dist-info/WHEEL
pyke_mcp-0.1.1.dist-info/entry_points.txt
pyke_mcp-0.1.1.dist-info/licenses/LICENSE
pyke_mcp-0.1.1.dist-info/RECORD
