Metadata-Version: 2.4
Name: pyke-mcp
Version: 0.1.1
Summary: MCP server for Pyke logic programming engine
Author: David Xu
License: MIT
License-File: LICENSE
Keywords: inference-engine,logic-programming,mcp,pyke
Classifier: Development Status :: 3 - Alpha
Classifier: Intended Audience :: Developers
Classifier: License :: OSI Approved :: MIT License
Classifier: Programming Language :: Python :: 3
Classifier: Programming Language :: Python :: 3.10
Classifier: Programming Language :: Python :: 3.11
Classifier: Programming Language :: Python :: 3.12
Requires-Python: >=3.10
Requires-Dist: mcp>=1.2.0
Requires-Dist: pyke>=1.1.1
Provides-Extra: dev
Requires-Dist: pytest-asyncio>=0.21.0; extra == 'dev'
Requires-Dist: pytest>=7.0.0; extra == 'dev'
